bliqtools/__init__.py
bliqtools/bigimage.py
bliqtools/envtest.py
bliqtools/extract_metadata.py
bliqtools/file_manager.py
bliqtools/image_loader.py
bliqtools/nirvana.py
bliqtools/testing.py
bliqtools/tests/__init__.py
bliqtools/tests/test_bigimage.py
bliqtools/tests/test_bigimage_performance.py
bliqtools/tests/test_bigimage_rgb.py
bliqtools/tests/test_file_manager.py
bliqtools/tests/test_image_loader.py
bliqtools/tests/test_nirvana.py
bliqtools/tests/test_testing.py
bliqtools-1.1.9.dist-info/LICENSE
bliqtools-1.1.9.dist-info/METADATA
bliqtools-1.1.9.dist-info/WHEEL
bliqtools-1.1.9.dist-info/top_level.txt
bliqtools-1.1.9.dist-info/RECORD
