Metadata-Version: 2.2
Name: bliqtools
Version: 1.1.9
Summary: A simple module for testing used at Bliq Photonics
Author-email: Daniel Côté <daniel@bliqphotonics.com>
Maintainer-email: Daniel Côté <daniel@bliqphotonics.com>
License: MIT License
Classifier: Development Status :: 4 - Beta
Classifier: Topic :: Software Development :: Build Tools
Classifier: Programming Language :: Python :: 3
Classifier: Programming Language :: Python :: 3.12
License-File: LICENSE
Requires-Dist: psutil
Requires-Dist: numpy
Requires-Dist: pyometiff
Requires-Dist: matplotlib
Requires-Dist: tifffile
Requires-Dist: Pillow
Requires-Dist: natsort
